askbob/__init__.py
askbob/__main__.py
askbob/loop.py
askbob/setup.py
askbob/util.py
askbob/action/__init__.py
askbob/action/responder.py
askbob/action/server.py
askbob/plugin/__init__.py
askbob/plugin/config.py
askbob/server/__init__.py
askbob/server/routes.py
askbob/server/voice.py
askbob/speech/__init__.py
askbob/speech/synthesiser.py
askbob/speech/transcriber.py
askbob/speech/listener/__init__.py
askbob/speech/listener/file.py
askbob/speech/listener/listener.py
askbob/speech/listener/mic.py
askbob-0.0.4.dist-info/LICENSE
askbob-0.0.4.dist-info/METADATA
askbob-0.0.4.dist-info/WHEEL
askbob-0.0.4.dist-info/top_level.txt
askbob-0.0.4.dist-info/RECORD
