Metadata-Version: 2.1
Name: askbob
Version: 0.0.4
Summary: A customisable, federated, privacy-safe voice assistant deployable on low-power devices.
Home-page: https://github.com/UCL-COMP0016-2020-Team-39/AskBob
Author: Jeremy Lo Ying Ping
Author-email: jeremylo2001@googlemail.com
License: UNKNOWN
Platform: UNKNOWN
Classifier: License :: OSI Approved :: GNU Affero General Public License v3
Requires-Dist: numpy (~=1.17.0)
Requires-Dist: spacy (~=2.2.4)
Requires-Dist: rasa[spacy] (~=2.2.9)
Requires-Dist: sanic (~=20.9.0)
Requires-Dist: Sanic-Cors (~=0.10.0.post3)
Requires-Dist: coloredlogs (~=10.0)
Provides-Extra: docs
Requires-Dist: sphinx (~=3.4.3) ; extra == 'docs'
Requires-Dist: recommonmark (~=0.7.1) ; extra == 'docs'
Requires-Dist: sphinx-rtd-theme (~=0.5.1) ; extra == 'docs'
Provides-Extra: interactive
Requires-Dist: halo (~=0.0.18) ; extra == 'interactive'
Requires-Dist: pyaudio (~=0.2.11) ; extra == 'interactive'
Requires-Dist: pyttsx3 (~=2.90) ; extra == 'interactive'
Requires-Dist: deepspeech (~=0.9.3) ; extra == 'interactive'
Requires-Dist: scipy (>=1.1.0) ; extra == 'interactive'
Requires-Dist: webrtcvad (~=2.0.10) ; extra == 'interactive'
Provides-Extra: test
Requires-Dist: pytest (~=6.2.1) ; extra == 'test'
Requires-Dist: pytest-cov (~=2.11.1) ; extra == 'test'
Requires-Dist: pytest-asyncio (~=0.14.0) ; extra == 'test'
Requires-Dist: pytest-sanic (~=1.7.0) ; extra == 'test'
Provides-Extra: voice
Requires-Dist: deepspeech (~=0.9.3) ; extra == 'voice'
Requires-Dist: scipy (>=1.1.0) ; extra == 'voice'
Requires-Dist: webrtcvad (~=2.0.10) ; extra == 'voice'
